{"type":"PR","pr":{"number":36,"head":"746a56d8d69d65f42c52670a7a61dc83f926dc9c"},"user":"Alexandresl","status":"draft","branch":"cms/2019-10-27-criando-layouts-2ª-parte-propriedades-flexbox","collection":"posts","title":"Criando layouts - 2ª parte - Propriedades Flexbox","description":"Vamos conhecer as propriedades que poderão ser utilizadas para a manipulação de um contêiner Flexbox.","objects":{"entry":{"path":"posts/2019-10-27-criando-layouts-2ª-parte-propriedades-flexbox.md","sha":"08d7e4afec757bcbffad5ceabb49836e98d3b391"},"files":[]},"timeStamp":"2019-10-28T05:25:18.951Z"}